myprss/__init__.py
myprss/config.py
myprss/logger.py
myprss/main.py
myprss/parser.py
myprss/reader.py
myprss/registry.py
myprss/utils.py
myprss-0.2.3.dist-info/entry_points.txt
myprss-0.2.3.dist-info/LICENSE
myprss-0.2.3.dist-info/WHEEL
myprss-0.2.3.dist-info/METADATA
myprss-0.2.3.dist-info/RECORD
