Metadata-Version: 2.1
Name: myprss
Version: 0.2.3
Summary: rss reader for terminal
Author: rarnal
Author-email: arnal.romain@gmail.com
Requires-Python: >=3.7,<4.0
Classifier: Programming Language :: Python :: 3
Classifier: Programming Language :: Python :: 3.7
Classifier: Programming Language :: Python :: 3.8
Requires-Dist: click (>=7.1.2,<8.0.0)
Requires-Dist: defusedxml (>=0.6.0,<0.7.0)
Requires-Dist: requests (>=2.23.0,<3.0.0)
